[
  {
    "id": "emg-01",
    "name": "NBO Eco-Pure Tumbler",
    "price": 28000,
    "material": "Медицинская нержавеющая сталь SUS316",
    "volume": "500ml",
    "features": "Двойные вакуумные стенки, сохранение тепла до 12 часов, холодного — до 24 часов.",
    "eco_info": "100% перерабатываемые материалы, BPA-free (без бисфенола А).",
    "packaging": "Коробка из переработанного гофрокартона, обертка из крафт-бумаги (без пластиковой пленки).",
    "certifications": "FDA (США), LFGB (Германия), Эко-сертификат соответствия KCL.",
    "image_url": "images/tumbler_black.jpg"
  },
  {
    "id": "emg-02",
    "name": "NBO Green Leaf Daily",
    "price": 34000,
    "material": "Пищевая нержавеющая сталь SUS304, бамбуковое покрытие крышки",
    "volume": "450ml",
    "features": "Сверхлегкий корпус, матовое порошковое напыление против царапин, ситечко для чая.",
    "eco_info": "При производстве выделяется на 45% меньше CO2 по сравнению с аналогами.",
    "packaging": "Мешочек из натурального льна, картонный тубус из вторичного сырья.",
    "certifications": "Сертификат углеродной нейтральности Carbon Trust, СЕ маркировка.",
    "image_url": "images/tumbler_green.jpg"
  },
  {
    "id": "emg-03",
    "name": "NBO Ocean Saver Pocket",
    "price": 19500,
    "material": "Пищевой силикон высшего качества, сталь SUS304",
    "volume": "350ml",
    "features": "Складной компактный дизайн, герметичный клапан, защита от ожогов.",
    "eco_info": "Часть средств от продажи идет на очистку океана от пластика.",
    "packaging": "Минималистичный конверт из прессованной макулатуры с соевыми чернилами.",
    "certifications": "SGS Food Grade Test, Сертификат безопасности материалов MSDS.",
    "image_url": "images/tumbler_compact.jpg"
  }
]